tfjs_mnist/__init__.py
tfjs_mnist/static/index.html
tfjs_mnist/static/mnist.js
tfjs_mnist/static/mnist_images.png
tfjs_mnist/static/mnist_labels_uint8
tfjs_mnist/static/tufte.css
nb_tfjs_mnist-0.0.1.dist-info/LICENSE
nb_tfjs_mnist-0.0.1.dist-info/METADATA
nb_tfjs_mnist-0.0.1.dist-info/WHEEL
nb_tfjs_mnist-0.0.1.dist-info/entry_points.txt
nb_tfjs_mnist-0.0.1.dist-info/top_level.txt
nb_tfjs_mnist-0.0.1.dist-info/RECORD
