Metadata-Version: 2.1
Name: nb-tfjs-mnist
Version: 0.0.1
Summary: Jupyter notebook server proxy extension for tfjs (MNIST)
Home-page: https://github.com/innovationOUtside/serverproxy_tfjs_demos
Author: Tony Hirst
Author-email: tony.hirst@open.ac.uk
License: UNKNOWN
Platform: UNKNOWN
Requires-Dist: jupyter-server-proxy
Requires-Dist: notebook
